setup.py
github_licker.egg-info/PKG-INFO
github_licker.egg-info/SOURCES.txt
github_licker.egg-info/dependency_links.txt
github_licker.egg-info/entry_points.txt
github_licker.egg-info/requires.txt
github_licker.egg-info/top_level.txt
github_licker.egg-info/zip-safe
licker/__init__.py
scripts/licker