Metadata-Version: 1.1
Name: github-licker
Version: 0.0.1
Summary: Licker - Your Github License Checker for Organisational Repositories.
Home-page: https://github.com/jbspeakr/github-licker
Author: Jan Brennenstuhl
Author-email: jan@brennenstuhl.me
License: Apache License 2.0
Platform: UNKNOWN
Classifier: Development Status :: 4 - Beta
Classifier: Environment :: Console
Classifier: Intended Audience :: Developers
Classifier: Intended Audience :: System Administrators
Classifier: Programming Language :: Python :: 3 :: Only
